rest_api_supporter/__init__.py
rest_api_supporter/utils/__init__.py
rest_api_supporter/utils/base64_decode_audio.py
rest_api_supporter/utils/base64_decode_image.py
rest_api_supporter/utils/base64_decode_video.py
rest_api_supporter/utils/base64_encode_audio.py
rest_api_supporter/utils/base64_encode_image.py
rest_api_supporter/utils/base64_encode_video.py
rest_api_supporter-0.0.33.dist-info/METADATA
rest_api_supporter-0.0.33.dist-info/WHEEL
rest_api_supporter-0.0.33.dist-info/top_level.txt
rest_api_supporter-0.0.33.dist-info/RECORD
