Metadata-Version: 2.1
Name: rest-api-supporter
Version: 0.0.33
Summary: Rest api supporter
Home-page: https://github.com/automatethem/rest-api-supporter
Author: Sang Ki Kwon
Author-email: automatethem@gmail.com
License: MIT
Requires-Dist: pillow
Requires-Dist: soundfile
Requires-Dist: librosa
Requires-Dist: opencv-python (==4.7.0.72)
